d2b_dcm2niix.py
d2b_dcm2niix-1.0.0.dist-info/entry_points.txt
d2b_dcm2niix-1.0.0.dist-info/WHEEL
d2b_dcm2niix-1.0.0.dist-info/METADATA
d2b_dcm2niix-1.0.0.dist-info/RECORD
